brightpy/__init__.py
brightpy/__main__.py
brightpy/argparse_subparser_alias.py
BrightPy-0.1.2.dist-info/METADATA
BrightPy-0.1.2.dist-info/WHEEL
BrightPy-0.1.2.dist-info/entry_points.txt
BrightPy-0.1.2.dist-info/top_level.txt
BrightPy-0.1.2.dist-info/RECORD
