Metadata-Version: 2.1
Name: BrightPy
Version: 0.1.2
Summary: Control the backlight through sysfs.
Home-page: https://github.com/Cheaterman/BriPy
Author: Cheaterman
Author-email: the.cheaterman@gmail.com
License: MIT
Platform: UNKNOWN
Classifier: Programming Language :: Python :: 3
Classifier: License :: OSI Approved :: MIT License
Classifier: Operating System :: OS Independent
Requires-Python: >=3.6
